{
    "获取子文件夹列表": {
        "prefix": "获取子文件夹列表",
        "body": [
            "获取子文件夹列表(路径)"
        ],
        "description": "获取目录下的所有子目录"
    },
    "检测文件夹": {
        "prefix": "检测文件夹",
        "body": [
            "检测文件夹(路径)"
        ],
        "description": "判断目录是否存在"
    },
    "创建文件夹": {
        "prefix": "创建文件夹",
        "body": [
            "创建文件夹(路径)"
        ],
        "description": "创建目录"
    },
    "移动文件夹": {
        "prefix": "移动文件夹",
        "body": [
            "移动文件夹(源路径, 目标路径)"
        ],
        "description": "移动目录"
    },
    "删除文件夹": {
        "prefix": "删除文件夹",
        "body": [
            "删除文件夹(路径)"
        ],
        "description": "删除目录"
    },
    "删除文件夹及子项": {
        "prefix": "删除文件夹及子项",
        "body": [
            "删除文件夹及子项(路径)"
        ],
        "description": "删除目录及所有子目录"
    }
}